TelescopeML/DataMaster.py
TelescopeML/DeepTrainer.py
TelescopeML/DeepTuner.py
TelescopeML/IO_utils.py
TelescopeML/Predictor.py
TelescopeML/StatVisAnalyzer.py
TelescopeML/__init__.py
TelescopeML/__version__.py
TelescopeML-0.0.5.dist-info/LICENSE
TelescopeML-0.0.5.dist-info/METADATA
TelescopeML-0.0.5.dist-info/WHEEL
TelescopeML-0.0.5.dist-info/top_level.txt
TelescopeML-0.0.5.dist-info/RECORD
