Metadata-Version: 2.1
Name: TelescopeML
Version: 0.0.5
Summary: An End-to-End Python Package for Interpreting Telescope Datasets through Training Machine Learning Models, Generating Statistical Reports, and Visualizing Results
Home-page: https://ehsangharibnezhad.github.io/TelescopeML
Download-URL: https://github.com/EhsanGharibNezhad/TelescopeML
Author: Ehsan (Sam) Gharib-Nezhad
Author-email: e.gharibnezhad@gmail.com
License: GPL-3.0
Keywords: Astronomy,Stars,Telescope,CNN,Deep Learning,Machine Learning
Classifier: Intended Audience :: Science/Research
Classifier: License :: OSI Approved :: GNU General Public License v3 (GPLv3)
Classifier: Operating System :: OS Independent
Classifier: Programming Language :: Python
Classifier: Programming Language :: Python :: 3
Classifier: Topic :: Scientific/Engineering :: Astronomy
Classifier: Topic :: Software Development :: Libraries :: Python Modules
License-File: LICENSE
Requires-Dist: numpy ==1.26.1
Requires-Dist: bokeh
Requires-Dist: pandas ==2.0.3
Requires-Dist: astropy
Requires-Dist: matplotlib
Requires-Dist: seaborn ==0.12.2
Requires-Dist: sphinx ==7.2.6
Requires-Dist: scipy ==1.11.1
Requires-Dist: keras ==2.14.0
Requires-Dist: tensorflow ==2.14.0
Requires-Dist: jupyterlab
Requires-Dist: sphinx
Requires-Dist: spectres ==2.2.0
Requires-Dist: scikit-learn ==1.3.0
